conversations/__init__.py
conversations/forms.py
conversations/models.py
conversations/utils.py
conversations/views.py
conversations/migrations/201802171929_0625bc75ab77_add_conversations.py
conversations/templates/_inject_navlink.html
conversations/templates/_inject_new_message_button.html
conversations/templates/_inject_new_message_link.html
conversations/templates/conversation.html
conversations/templates/conversation_list.html
conversations/templates/drafts.html
conversations/templates/inbox.html
conversations/templates/message_form.html
conversations/templates/message_layout.html
conversations/templates/sent.html
conversations/templates/trash.html
conversations/translations/messages.pot
conversations/translations/en/LC_MESSAGES/messages.mo
conversations/translations/en/LC_MESSAGES/messages.po
flaskbb_plugin_conversations-1.1.1.dist-info/METADATA
flaskbb_plugin_conversations-1.1.1.dist-info/WHEEL
flaskbb_plugin_conversations-1.1.1.dist-info/entry_points.txt
flaskbb_plugin_conversations-1.1.1.dist-info/top_level.txt
flaskbb_plugin_conversations-1.1.1.dist-info/RECORD
