Metadata-Version: 2.1
Name: flaskbb-plugin-conversations
Version: 1.1.1
Summary: A private messaging plugin for FlaskBB
Home-page: https://flaskbb.org
Author: Peter Justin
Author-email: peter.justin@outlook.com
License: BSD License
Project-URL: Code, https://github.com/flaskbb/flaskbb-plugin-conversations
Project-URL: Issue Tracker, https://github.com/flaskbb/flaskbb-plugin-conversations/issues
Keywords: flaskbb plugin conversations messaging
Platform: any
Classifier: Development Status :: 5 - Production/Stable
Classifier: Environment :: Web Environment
Classifier: Environment :: Plugins
Classifier: Framework :: Flask
Classifier: Intended Audience :: Developers
Classifier: License :: OSI Approved :: BSD License
Classifier: Operating System :: OS Independent
Classifier: Programming Language :: Python
Classifier: Programming Language :: Python :: 3
Classifier: Topic :: Internet :: WWW/HTTP :: Dynamic Content
Classifier: Topic :: Software Development :: Libraries :: Python Modules
Requires-Dist: FlaskBB (>=2.1.0)
